[{"code":"100","name":"本店営業部","kana":"ホンテン","hira":"ほんてん"},{"code":"101","name":"徳島駅前","kana":"トクシマエキマエ","hira":"とくしまえきまえ"},{"code":"102","name":"佐古","kana":"サコ","hira":"さこ"},{"code":"103","name":"二軒屋","kana":"ニケンヤ","hira":"にけんや"},{"code":"104","name":"県庁","kana":"ケンチヨウ","hira":"けんちよう"},{"code":"105","name":"津田","kana":"ツダ","hira":"つだ"},{"code":"106","name":"福島","kana":"フクシマ","hira":"ふくしま"},{"code":"107","name":"渭北","kana":"イホク","hira":"いほく"},{"code":"108","name":"両国橋","kana":"リヨウゴクバシ","hira":"りようごくばし"},{"code":"109","name":"佐古東","kana":"サコヒガシ","hira":"さこひがし"},{"code":"110","name":"昭和町","kana":"シヨウワチヨウ","hira":"しようわちよう"},{"code":"111","name":"助任橋","kana":"スケトウバシ","hira":"すけとうばし"},{"code":"112","name":"田宮","kana":"タミヤ","hira":"たみや"},{"code":"113","name":"末広","kana":"スエヒロ","hira":"すえひろ"},{"code":"114","name":"鮎喰","kana":"アクイ","hira":"あくい"},{"code":"115","name":"問屋町","kana":"トイヤマチ","hira":"といやまち"},{"code":"116","name":"中央市場","kana":"チユウオウイチバ","hira":"ちゆうおういちば"},{"code":"117","name":"蔵本","kana":"クラモト","hira":"くらもと"},{"code":"120","name":"かちどき橋","kana":"カチドキバシ","hira":"かちどきばし"},{"code":"121","name":"法花","kana":"ホツケ","hira":"ほつけ"},{"code":"122","name":"住吉","kana":"スミヨシ","hira":"すみよし"},{"code":"123","name":"八万","kana":"ハチマン","hira":"はちまん"},{"code":"127","name":"矢三","kana":"ヤソ","hira":"やそ"},{"code":"128","name":"新聞放送会館出張所","kana":"シンブンホウソウカイカン","hira":"しんぶんほうそうかいかん"},{"code":"131","name":"徳島市役所","kana":"トクシマシヤクシヨ","hira":"とくしましやくしよ"},{"code":"132","name":"マリンピア","kana":"マリンピア","hira":"まりんぴあ"},{"code":"201","name":"小松島","kana":"コマツシマ","hira":"こまつしま"},{"code":"202","name":"勝浦","kana":"カツウラ","hira":"かつうら"},{"code":"203","name":"羽ノ浦","kana":"ハノウラ","hira":"はのうら"},{"code":"204","name":"古庄","kana":"フルシヨウ","hira":"ふるしよう"},{"code":"205","name":"中島","kana":"ナカシマ","hira":"なかしま"},{"code":"206","name":"阿南","kana":"アナン","hira":"あなん"},{"code":"207","name":"橘","kana":"タチバナ","hira":"たちばな"},{"code":"208","name":"新野","kana":"アラタノ","hira":"あらたの"},{"code":"209","name":"鷲敷","kana":"ワジキ","hira":"わじき"},{"code":"210","name":"平谷","kana":"ヒラダニ","hira":"ひらだに"},{"code":"213","name":"由岐","kana":"ユキ","hira":"ゆき"},{"code":"214","name":"日和佐","kana":"ヒワサ","hira":"ひわさ"},{"code":"215","name":"牟岐","kana":"ムギ","hira":"むぎ"},{"code":"216","name":"海南","kana":"カイナン","hira":"かいなん"},{"code":"217","name":"宍喰","kana":"シシクイ","hira":"ししくい"},{"code":"218","name":"中田","kana":"チユウデン","hira":"ちゆうでん"},{"code":"219","name":"赤石","kana":"アカイシ","hira":"あかいし"},{"code":"220","name":"見能林","kana":"ミノバヤシ","hira":"みのばやし"},{"code":"301","name":"鳴門","kana":"ナルト","hira":"なると"},{"code":"302","name":"瀬戸","kana":"セト","hira":"せと"},{"code":"304","name":"川内","kana":"カワウチ","hira":"かわうち"},{"code":"305","name":"松茂","kana":"マツシゲ","hira":"まつしげ"},{"code":"306","name":"北島","kana":"キタジマ","hira":"きたじま"},{"code":"307","name":"藍住","kana":"アイズミ","hira":"あいずみ"},{"code":"308","name":"板野","kana":"イタノ","hira":"いたの"},{"code":"309","name":"板東","kana":"バンドウ","hira":"ばんどう"},{"code":"310","name":"上板","kana":"カミイタ","hira":"かみいた"},{"code":"311","name":"鳴門東","kana":"ナルトヒガシ","hira":"なるとひがし"},{"code":"312","name":"勝瑞","kana":"シヨウズイ","hira":"しようずい"},{"code":"313","name":"藍住西","kana":"アイズミニシ","hira":"あいずみにし"},{"code":"314","name":"大津","kana":"オオツ","hira":"おおつ"},{"code":"315","name":"黒崎","kana":"クロサキ","hira":"くろさき"},{"code":"316","name":"徳島北","kana":"トクシマキタ","hira":"とくしまきた"},{"code":"401","name":"国府","kana":"コクフ","hira":"こくふ"},{"code":"402","name":"石井","kana":"イシイ","hira":"いしい"},{"code":"403","name":"鴨島","kana":"カモジマ","hira":"かもじま"},{"code":"404","name":"市場","kana":"イチバ","hira":"いちば"},{"code":"405","name":"川島","kana":"カワシマ","hira":"かわしま"},{"code":"406","name":"山川","kana":"ヤマカワ","hira":"やまかわ"},{"code":"407","name":"穴吹","kana":"アナブキ","hira":"あなぶき"},{"code":"408","name":"脇町","kana":"ワキマチ","hira":"わきまち"},{"code":"409","name":"貞光","kana":"サダミツ","hira":"さだみつ"},{"code":"410","name":"半田","kana":"ハンダ","hira":"はんだ"},{"code":"411","name":"三野","kana":"ミノ","hira":"みの"},{"code":"412","name":"加茂","kana":"カモ","hira":"かも"},{"code":"413","name":"池田","kana":"イケダ","hira":"いけだ"},{"code":"414","name":"美馬","kana":"ミマ","hira":"みま"},{"code":"415","name":"阿波町","kana":"アワチヨウ","hira":"あわちよう"},{"code":"416","name":"土成","kana":"ドナリ","hira":"どなり"},{"code":"417","name":"三好","kana":"ミヨシ","hira":"みよし"},{"code":"419","name":"山城","kana":"ヤマシロ","hira":"やましろ"},{"code":"420","name":"竜王","kana":"リユウオウ","hira":"りゆうおう"},{"code":"501","name":"高松","kana":"タカマツ","hira":"たかまつ"},{"code":"502","name":"高知","kana":"コウチ","hira":"こうち"},{"code":"503","name":"松山","kana":"マツヤマ","hira":"まつやま"},{"code":"504","name":"大阪","kana":"オオサカ","hira":"おおさか"},{"code":"505","name":"東京","kana":"トウキヨウ","hira":"とうきよう"},{"code":"506","name":"神戸","kana":"コウベ","hira":"こうべ"},{"code":"507","name":"西大阪","kana":"ニシオオサカ","hira":"にしおおさか"},{"code":"508","name":"堺","kana":"サカイ","hira":"さかい"},{"code":"509","name":"岡山","kana":"オカヤマ","hira":"おかやま"},{"code":"510","name":"尼崎","kana":"アマガサキ","hira":"あまがさき"},{"code":"511","name":"丸亀","kana":"マルガメ","hira":"まるがめ"},{"code":"512","name":"蒲田","kana":"カマタ","hira":"かまた"},{"code":"513","name":"北大阪","kana":"キタオオサカ","hira":"きたおおさか"},{"code":"514","name":"江戸川","kana":"エドガワ","hira":"えどがわ"},{"code":"515","name":"東大阪","kana":"ヒガシオオサカ","hira":"ひがしおおさか"},{"code":"516","name":"南大阪","kana":"ミナミオオサカ","hira":"みなみおおさか"},{"code":"517","name":"姫路","kana":"ヒメジ","hira":"ひめじ"},{"code":"518","name":"東京城北","kana":"トウキヨウジヨウホク","hira":"とうきようじようほく"},{"code":"519","name":"横浜","kana":"ヨコハマ","hira":"よこはま"},{"code":"520","name":"代々木","kana":"ヨヨギ","hira":"よよぎ"},{"code":"831","name":"提携エーテイーエム","kana":"テイケイエ－テイ－エム","hira":"ていけいえ－てい－えむ"},{"code":"839","name":"法人営業センター出張所","kana":"ホウジンエイギヨウセンタ－","hira":"ほうじんえいぎようせんた－"}]