[{"code":"001","name":"本店営業部","kana":"ホンテン","hira":"ほんてん"},{"code":"002","name":"牛久保","kana":"ウシクボ","hira":"うしくぼ"},{"code":"003","name":"諏訪","kana":"スワ","hira":"すわ"},{"code":"004","name":"国府","kana":"コウ","hira":"こう"},{"code":"005","name":"御津","kana":"ミト","hira":"みと"},{"code":"006","name":"小坂井","kana":"コザカイ","hira":"こざかい"},{"code":"007","name":"豊橋","kana":"トヨハシ","hira":"とよはし"},{"code":"009","name":"一宮","kana":"イチノミヤ","hira":"いちのみや"},{"code":"010","name":"豊橋西","kana":"トヨハシニシ","hira":"とよはしにし"},{"code":"011","name":"蒲郡","kana":"ガマゴオリ","hira":"がまごおり"},{"code":"012","name":"新桜","kana":"シンサクラ","hira":"しんさくら"},{"code":"013","name":"いなり","kana":"イナリ","hira":"いなり"},{"code":"014","name":"弥生","kana":"ヤヨイ","hira":"やよい"},{"code":"015","name":"御油","kana":"ゴユ","hira":"ごゆ"},{"code":"016","name":"三ノ輪","kana":"ミノワ","hira":"みのわ"},{"code":"017","name":"八南","kana":"ハチナン","hira":"はちなん"},{"code":"019","name":"二川","kana":"フタガワ","hira":"ふたがわ"},{"code":"021","name":"音羽","kana":"オトワ","hira":"おとわ"},{"code":"022","name":"蔵子","kana":"ゾウシ","hira":"ぞうし"},{"code":"023","name":"牛川","kana":"ウシカワ","hira":"うしかわ"},{"code":"024","name":"蒲郡西","kana":"ガマゴオリニシ","hira":"がまごおりにし"},{"code":"025","name":"佐藤町","kana":"サトウチヨウ","hira":"さとうちよう"},{"code":"026","name":"大清水","kana":"オオシミズ","hira":"おおしみず"},{"code":"027","name":"鳳来","kana":"ホウライ","hira":"ほうらい"},{"code":"028","name":"田原","kana":"タハラ","hira":"たはら"},{"code":"029","name":"豊","kana":"ユタカ","hira":"ゆたか"},{"code":"030","name":"三蔵子","kana":"サンゾウゴ","hira":"さんぞうご"},{"code":"031","name":"菰口","kana":"コモグチ","hira":"こもぐち"},{"code":"032","name":"藤沢","kana":"フジサワ","hira":"ふじさわ"},{"code":"034","name":"新城中央","kana":"シンシロチユウオウ","hira":"しんしろちゆうおう"},{"code":"036","name":"東栄","kana":"トウエイ","hira":"とうえい"},{"code":"040","name":"岡崎","kana":"オカザキ","hira":"おかざき"},{"code":"041","name":"本宿","kana":"モトジユク","hira":"もとじゆく"},{"code":"043","name":"幸田","kana":"コウタ","hira":"こうた"},{"code":"050","name":"インターネット","kana":"インタ－ネツト","hira":"いんた－ねつと"}]