[{"code":"121","name":"浅草","kana":"アサクサ","hira":"あさくさ"},{"code":"124","name":"足立","kana":"アダチ","hira":"あだち"},{"code":"001","name":"品川駅東口","kana":"シナガワエキヒガシグチ","hira":"しながわえきひがしぐち"},{"code":"002","name":"本店営業部","kana":"ホンテン","hira":"ほんてん"},{"code":"003","name":"十条","kana":"ジユウジヨウ","hira":"じゆうじよう"},{"code":"004","name":"目黒","kana":"メグロ","hira":"めぐろ"},{"code":"005","name":"高円寺","kana":"コウエンジ","hira":"こうえんじ"},{"code":"006","name":"亀戸","kana":"カメイド","hira":"かめいど"},{"code":"007","name":"蒲田","kana":"カマタ","hira":"かまた"},{"code":"008","name":"日暮里","kana":"ニツポリ","hira":"につぽり"},{"code":"009","name":"新宿","kana":"シンジユク","hira":"しんじゆく"},{"code":"010","name":"三軒茶屋","kana":"サンゲンヂヤヤ","hira":"さんげんぢやや"},{"code":"011","name":"新小岩","kana":"シンコイワ","hira":"しんこいわ"},{"code":"012","name":"大塚","kana":"オオツカ","hira":"おおつか"},{"code":"013","name":"銀座","kana":"ギンザ","hira":"ぎんざ"},{"code":"014","name":"吉祥寺","kana":"キチジヨウジ","hira":"きちじようじ"},{"code":"015","name":"恵比寿","kana":"エビス","hira":"えびす"},{"code":"016","name":"常盤台","kana":"トキワダイ","hira":"ときわだい"},{"code":"018","name":"戸越","kana":"トゴシ","hira":"とごし"},{"code":"019","name":"府中","kana":"フチユウ","hira":"ふちゆう"},{"code":"020","name":"押上","kana":"オシアゲ","hira":"おしあげ"},{"code":"021","name":"田町駅前","kana":"タマチエキマエ","hira":"たまちえきまえ"},{"code":"022","name":"荏原町駅前","kana":"エバラマチエキマエ","hira":"えばらまちえきまえ"},{"code":"023","name":"福生","kana":"フツサ","hira":"ふつさ"},{"code":"025","name":"品川","kana":"シナガワ","hira":"しながわ"},{"code":"027","name":"西蒲田","kana":"ニシカマタ","hira":"にしかまた"},{"code":"029","name":"大井","kana":"オオイ","hira":"おおい"},{"code":"031","name":"八王子営業部","kana":"ハチオウジ","hira":"はちおうじ"},{"code":"032","name":"日野","kana":"ヒノ","hira":"ひの"},{"code":"034","name":"西八","kana":"ニシハチ","hira":"にしはち"},{"code":"035","name":"石川","kana":"イシカワ","hira":"いしかわ"},{"code":"036","name":"青山","kana":"アオヤマ","hira":"あおやま"},{"code":"037","name":"保谷","kana":"ホウヤ","hira":"ほうや"},{"code":"038","name":"立川","kana":"タチカワ","hira":"たちかわ"},{"code":"039","name":"堀ノ内","kana":"ホリノウチ","hira":"ほりのうち"},{"code":"044","name":"三鷹","kana":"ミタカ","hira":"みたか"},{"code":"045","name":"東大和","kana":"ヒガシヤマト","hira":"ひがしやまと"},{"code":"046","name":"荻窪","kana":"オギクボ","hira":"おぎくぼ"},{"code":"047","name":"富士見台","kana":"フジミダイ","hira":"ふじみだい"}]