[{"code":"001","name":"本店","kana":"ホンテン","hira":"ほんてん"},{"code":"002","name":"下総","kana":"シモフサ","hira":"しもふさ"},{"code":"005","name":"神崎","kana":"コウザキ","hira":"こうざき"},{"code":"006","name":"大栄","kana":"タイエイ","hira":"たいえい"},{"code":"010","name":"小見川","kana":"オミガワ","hira":"おみがわ"},{"code":"015","name":"山田","kana":"ヤマダ","hira":"やまだ"},{"code":"021","name":"東庄","kana":"トウノシヨウ","hira":"とうのしよう"},{"code":"025","name":"栗源","kana":"クリモト","hira":"くりもと"},{"code":"026","name":"佐原","kana":"サワラ","hira":"さわら"},{"code":"027","name":"多古","kana":"タコ","hira":"たこ"}]