[{"code":"104","name":"日進","kana":"ニツシン","hira":"につしん"},{"code":"201","name":"東郷","kana":"トウゴウ","hira":"とうごう"},{"code":"228","name":"春木","kana":"ハルキ","hira":"はるき"},{"code":"309","name":"豊明","kana":"トヨアケ","hira":"とよあけ"},{"code":"341","name":"豊明栄","kana":"トヨアケサカエ","hira":"とよあけさかえ"},{"code":"406","name":"瀬戸","kana":"セト","hira":"せと"},{"code":"414","name":"山口","kana":"ヤマグチ","hira":"やまぐち"},{"code":"449","name":"水野","kana":"ミズノ","hira":"みずの"},{"code":"457","name":"品野","kana":"シナノ","hira":"しなの"},{"code":"503","name":"尾張旭","kana":"オワリアサヒ","hira":"おわりあさひ"},{"code":"538","name":"尾張旭東","kana":"オワリアサヒヒガシ","hira":"おわりあさひひがし"},{"code":"546","name":"本地ケ原","kana":"ホンジガハラ","hira":"ほんじがはら"},{"code":"601","name":"長久手","kana":"ナガクテ","hira":"ながくて"},{"code":"619","name":"長久手西","kana":"ナガクテニシ","hira":"ながくてにし"},{"code":"015","name":"本店","kana":"ホンテン","hira":"ほんてん"},{"code":"023","name":"米野木","kana":"コメノキ","hira":"こめのき"},{"code":"031","name":"岩崎","kana":"イワサキ","hira":"いわさき"},{"code":"040","name":"浅田","kana":"アサダ","hira":"あさだ"}]