[{"code":"101","name":"本店","kana":"ホンテン","hira":"ほんてん"},{"code":"104","name":"板野","kana":"イタノ","hira":"いたの"},{"code":"106","name":"藍住","kana":"アイズミ","hira":"あいずみ"},{"code":"107","name":"北島","kana":"キタジマ","hira":"きたじま"},{"code":"109","name":"阿波","kana":"アワ","hira":"あわ"},{"code":"113","name":"上板","kana":"カミイタ","hira":"かみいた"},{"code":"120","name":"名西","kana":"ミヨウザイ","hira":"みようざい"},{"code":"121","name":"神山","kana":"カミヤマ","hira":"かみやま"},{"code":"130","name":"鳴門","kana":"ナルト","hira":"なると"},{"code":"131","name":"うずしお","kana":"ウズシオ","hira":"うずしお"},{"code":"140","name":"桑野","kana":"クワノ","hira":"くわの"},{"code":"141","name":"阿南","kana":"アナン","hira":"あなん"},{"code":"142","name":"上中","kana":"カミナカ","hira":"かみなか"},{"code":"143","name":"福井","kana":"フクイ","hira":"ふくい"},{"code":"144","name":"相生","kana":"アイオイ","hira":"あいおい"},{"code":"150","name":"海陽","kana":"カイヨウ","hira":"かいよう"},{"code":"151","name":"三波","kana":"ミナミ","hira":"みなみ"},{"code":"160","name":"あわ市","kana":"アワシ","hira":"あわし"},{"code":"161","name":"市場","kana":"イチバ","hira":"いちば"},{"code":"170","name":"麻植東部","kana":"オエトウブ","hira":"おえとうぶ"},{"code":"171","name":"麻植西部","kana":"オエセイブ","hira":"おえせいぶ"},{"code":"180","name":"脇町","kana":"ワキマチ","hira":"わきまち"},{"code":"181","name":"美馬","kana":"ミマ","hira":"みま"},{"code":"190","name":"三加茂","kana":"ミカモ","hira":"みかも"},{"code":"191","name":"池田","kana":"イケダ","hira":"いけだ"}]